linepy/__init__.py
linepy/auth.py
linepy/call.py
linepy/callback.py
linepy/channel.py
linepy/client.py
linepy/config.py
linepy/models.py
linepy/object.py
linepy/oepoll.py
linepy/server.py
linepy/session.py
linepy/square.py
linepy/talk.py
linepy/timeline.py
linepy-3.0.8.dist-info/DESCRIPTION.rst
linepy-3.0.8.dist-info/METADATA
linepy-3.0.8.dist-info/RECORD
linepy-3.0.8.dist-info/WHEEL
linepy-3.0.8.dist-info/metadata.json
linepy-3.0.8.dist-info/top_level.txt
